zpp/__init__.py
zpp/cli.py
zpp/hints_ai.py
zpp/hints_rule.py
zpp/metrics.py
zpp/runner.py
zpp/toolchain.py
zpp/ui_app.py
zpp/utils.py
zpp/watcher.py
zynpp-2.0.4.dist-info/METADATA
zynpp-2.0.4.dist-info/WHEEL
zynpp-2.0.4.dist-info/entry_points.txt
zynpp-2.0.4.dist-info/licenses/LICENSE
zynpp-2.0.4.dist-info/RECORD
