Metadata-Version: 2.4
Name: zynpp
Version: 2.0.4
Summary: ZPP: Zero-hassle C++ build/run, metrics, and optimization hints with a real-time terminal UI
Author: ZPP Authors
License: MIT
License-File: LICENSE
Keywords: benchmark,c++,cli,developer-tools,g++,optimization,textual
Classifier: Environment :: Console
Classifier: License :: OSI Approved :: MIT License
Classifier: Operating System :: MacOS
Classifier: Operating System :: Microsoft :: Windows
Classifier: Operating System :: POSIX :: Linux
Classifier: Programming Language :: Python :: 3
Classifier: Programming Language :: Python :: 3 :: Only
Classifier: Programming Language :: Python :: 3.10
Classifier: Programming Language :: Python :: 3.11
Classifier: Programming Language :: Python :: 3.12
Classifier: Topic :: Software Development :: Build Tools
Classifier: Topic :: System :: Benchmark
Requires-Python: <3.14,>=3.10
Requires-Dist: colorama==0.4.*; platform_system == 'Windows'
Requires-Dist: httpx==0.27.*
Requires-Dist: psutil==5.9.*
Requires-Dist: rich==13.8.*
Requires-Dist: textual==0.79.*
Requires-Dist: tomli-w==1.0.*
Requires-Dist: tomli==2.0.*; python_version < '3.11'
Requires-Dist: typer==0.12.*
Provides-Extra: dev
Requires-Dist: mypy==1.11.*; extra == 'dev'
Requires-Dist: pytest-xdist==3.6.*; extra == 'dev'
Requires-Dist: pytest==8.3.*; extra == 'dev'
Requires-Dist: ruff==0.6.*; extra == 'dev'
